COSMO_TL/GammaLoaders.py
COSMO_TL/NIST.py
COSMO_TL/__init__.py
COSMO_TL/custom.py
COSMO_TL/sigma_functions.py
COSMO_TL-0.1.0.0.dist-info/METADATA
COSMO_TL-0.1.0.0.dist-info/WHEEL
COSMO_TL-0.1.0.0.dist-info/top_level.txt
COSMO_TL-0.1.0.0.dist-info/RECORD
